[
{ "id": 1, "word": "謝ります", "kana": "あやまります" },
{ "id": 2, "word": "あいます", "kana": "あいます" },
{ "id": 3, "word": "事故にあいます", "kana": "じこにあいます" },
{ "id": 4, "word": "信じます", "kana": "しんじます" },
{ "id": 5, "word": "用意します", "kana": "よういします" },
{ "id": 6, "word": "キャンセルします", "kana": "キャンセルします" },
{ "id": 7, "word": "旨く行きます", "kana": "うまくいきます" },
{ "id": 8, "word": "保証書", "kana": "ほしょうしょ" },
{ "id": 9, "word": "領収書", "kana": "りょうしゅうしょ" },
{ "id": 10, "word": "贈物", "kana": "おくりもの" },
{ "id": 11, "word": "贈物をします", "kana": "おくりものをします" },
{ "id": 12, "word": "間違い電話", "kana": "まちがいでんわ" },
{ "id": 13, "word": "キャンプ", "kana": "キャンプ" },
{ "id": 14, "word": "係", "kana": "かかり" },
{ "id": 15, "word": "中止", "kana": "ちゅうし" },
{ "id": 16, "word": "点", "kana": "てん" },
{ "id": 17, "word": "レバー", "kana": "レバー" },
{ "id": 18, "word": "～円札", "kana": "～えんさつ" },
{ "id": 19, "word": "ちゃんと", "kana": "ちゃんと" },
{ "id": 20, "word": "急に", "kana": "きゅうに" },
{ "id": 21, "word": "楽しみにしています", "kana": "たのしみにしています" },
{ "id": 22, "word": "以上です", "kana": "いじょうです" },
{ "id": 23, "word": "係員", "kana": "かかりいん" },
{ "id": 24, "word": "コース", "kana": "コース" },
{ "id": 25, "word": "スタート", "kana": "スタート" },
{ "id": 26, "word": "～位", "kana": "～い" },
{ "id": 27, "word": "優勝します", "kana": "ゆうしょうします" },
{ "id": 28, "word": "悩み", "kana": "なやみ" },
{ "id": 29, "word": "目覚まし", "kana": "めざまし" },
{ "id": 30, "word": "眠ります", "kana": "ねむります" },
{ "id": 31, "word": "目が覚めます", "kana": "めがさめます" },
{ "id": 32, "word": "大学生", "kana": "だいがくせい" },
{ "id": 33, "word": "回答", "kana": "かいとう" },
{ "id": 34, "word": "鳴ります", "kana": "なります" },
{ "id": 35, "word": "セットします", "kana": "セットします" },
{ "id": 36, "word": "其れでも", "kana": "それでも" }
]